{
  "type": "Compass Connections",
  "version": {
    "$numberInt": "1"
  },
  "connections": [
    {
      "id": "6fdb8d95-a755-4e8d-ac43-b3dff386196d",
      "lastUsed": {
        "$date": {
          "$numberLong": "1744094586233"
        }
      },
      "savedConnectionType": "recent",
      "connectionOptions": {
        "connectionString": "mongodb://localhost:27017/",
        "oidc": {
          "serializedState": "eyJvaWRjUGx1Z2luU3RhdGVWZXJzaW9uIjowLCJzdGF0ZSI6W119"
        }
      }
    }
  ]
}